[{"createdDate":982666800000,"updatedDate":1400072112000,"rowStatus":"A","isActive":"A","expressionId":1,"expressionText":{"criteria":"0","operation":">","value":"20","keyword":"*"},"projectId":1,"ownerId":1,"email":"ilker.colakoglu@etiya.com","alarmInterval":2},{"createdDate":982666800000,"updatedDate":982666800000,"rowStatus":"A","isActive":"A","expressionId":2,"expressionText":{"criteria":"0","operation":">","value":"10","keyword":"fener"},"projectId":1,"ownerId":1,"email":"ilker.colakoglu@etiya.com","alarmInterval":4}]
